ckanny/__init__.py
ckanny/datastorer.py
ckanny/filestorer.py
ckanny/hdx.py
ckanny/package.py
ckanny-0.17.2.data/scripts/ckanny
ckanny-0.17.2.dist-info/DESCRIPTION.rst
ckanny-0.17.2.dist-info/METADATA
ckanny-0.17.2.dist-info/pydist.json
ckanny-0.17.2.dist-info/RECORD
ckanny-0.17.2.dist-info/top_level.txt
ckanny-0.17.2.dist-info/WHEEL
