Metadata-Version: 2.0
Name: ckanny
Version: 0.17.2
Summary: Miscellaneous CKAN utility scripts
Home-page: https://github.com/reubano/ckanny
Author: Reuben Cummings
Author-email: reubano@gmail.com
License: MIT
Download-URL: https://github.com/reubano/ckanny/downloads/ckanny*.tgz
Keywords: ckanny
Platform: MacOS X
Platform: Windows
Platform: Linux
Classifier: License :: OSI Approved :: MIT License
Classifier: Development Status :: 4 - Beta
Classifier: Natural Language :: English
Classifier: Programming Language :: Python :: 2
Classifier: Programming Language :: Python :: 2.7
Classifier: Environment :: Console
Classifier: Intended Audience :: Developers
Classifier: Intended Audience :: End Users/Desktop
Classifier: Operating System :: POSIX
Classifier: Operating System :: MacOS :: MacOS X
Classifier: Operating System :: POSIX :: Linux
Requires-Dist: manage.py (==0.2.10)
Requires-Dist: xattr (==0.7.5)
Requires-Dist: tabutils (==0.23.1)
Requires-Dist: ckanutils (==0.14.8)
Requires-Dist: pkutils (==0.6.1)
